[
    {
        "event_id": "1766857859339",
        "device_id": "D-028",
        "patient_id": "PT-1024",
        "timestamp": "2025-12-27 23:20:59",
        "heart_rate": 96,
        "oxygen_level": 97,
        "status": "Normal",
        "battery_level": 67
    },
    {
        "event_id": "1766857860341",
        "device_id": "D-048",
        "patient_id": "PT-1084",
        "timestamp": "2025-12-27 23:21:00",
        "heart_rate": 60,
        "oxygen_level": 97,
        "status": "Normal",
        "battery_level": 74
    },
    {
        "event_id": "1766857861343",
        "device_id": "D-050",
        "patient_id": "PT-1015",
        "timestamp": "2025-12-27 23:21:01",
        "heart_rate": 95,
        "oxygen_level": 97,
        "status": "Normal",
        "battery_level": 96
    },
    {
        "event_id": "1766857862345",
        "device_id": "D-056",
        "patient_id": "PT-1095",
        "timestamp": "2025-12-27 23:21:02",
        "heart_rate": 99,
        "oxygen_level": 97,
        "status": "Normal",
        "battery_level": 67
    },
    {
        "event_id": "1766857863348",
        "device_id": "D-019",
        "patient_id": "PT-1008",
        "timestamp": "2025-12-27 23:21:03",
        "heart_rate": 85,
        "oxygen_level": 96,
        "status": "Normal",
        "battery_level": 59
    },
    {
        "event_id": "1766857864350",
        "device_id": "D-041",
        "patient_id": "PT-1098",
        "timestamp": "2025-12-27 23:21:04",
        "heart_rate": 67,
        "oxygen_level": 97,
        "status": "Normal",
        "battery_level": 77
    },
    {
        "event_id": "1766857865351",
        "device_id": "D-042",
        "patient_id": "PT-1032",
        "timestamp": "2025-12-27 23:21:05",
        "heart_rate": 85,
        "oxygen_level": 97,
        "status": "Normal",
        "battery_level": 45
    },
    {
        "event_id": "1766857866353",
        "device_id": "D-049",
        "patient_id": "PT-1046",
        "timestamp": "2025-12-27 23:21:06",
        "heart_rate": 173,
        "oxygen_level": 82,
        "status": "CRITICAL",
        "battery_level": 86
    },
    {
        "event_id": "1766857867356",
        "device_id": "D-085",
        "patient_id": "PT-1026",
        "timestamp": "2025-12-27 23:21:07",
        "heart_rate": 89,
        "oxygen_level": 99,
        "status": "Normal",
        "battery_level": 32
    },
    {
        "event_id": "1766857868358",
        "device_id": "D-090",
        "patient_id": "PT-1004",
        "timestamp": "2025-12-27 23:21:08",
        "heart_rate": 70,
        "oxygen_level": 95,
        "status": "Normal",
        "battery_level": 45
    }
]